{
  "aor": 0.0007540182648401826,
  "aqi": 0.016781803652968035,
  "bids_meta": {
    "RepetitionTime": 2,
    "TaskName": "SocialRiskyChoice",
    "dataset": "ds001883",
    "modality": "bold",
    "run_id": 3,
    "session_id": "01",
    "subject_id": "05",
    "task_id": "SRC"
  },
  "dummy_trs": 0,
  "dvars_nstd": 80.14528061041277,
  "dvars_std": 1.0215600586238531,
  "dvars_vstd": 1.0115178603211008,
  "efc": 0.6194760580287639,
  "fber": 141.9515838623047,
  "fd_mean": 0.1390130434319428,
  "fd_num": 34,
  "fd_perc": 15.525114155251142,
  "fwhm_avg": 3.1399644444444443,
  "fwhm_x": 2.8903733333333332,
  "fwhm_y": 3.3001666666666662,
  "fwhm_z": 3.2293533333333335,
  "gcor": 0.00194436,
  "gsr_x": -0.01748533546924591,
  "gsr_y": 0.0751611590385437,
  "provenance": {
    "md5sum": "3f51cb9306d06b0410a0c5553c1ebf31",
    "settings": {
      "fd_thres": 0.2,
      "testing": false
    },
    "software": "mriqc",
    "version": "22.0.1",
    "webapi_port": null,
    "webapi_url": "https://mriqc.nimh.nih.gov/api/v1"
  },
  "size_t": 219,
  "size_x": 128,
  "size_y": 128,
  "size_z": 81,
  "snr": 2.1977189552933125,
  "spacing_tr": 2.0,
  "spacing_x": 1.5,
  "spacing_y": 1.5,
  "spacing_z": 1.5,
  "summary_bg_k": 89.01556018751192,
  "summary_bg_mad": 13.153858585944139,
  "summary_bg_mean": 74.20813751220703,
  "summary_bg_median": 48.93606948852539,
  "summary_bg_n": 773488.0,
  "summary_bg_p05": 36.72602462768555,
  "summary_bg_p95": 184.2739715576172,
  "summary_bg_stdv": 99.16555786132812,
  "summary_fg_k": 2.394961926038973,
  "summary_fg_mad": 233.58769417528106,
  "summary_fg_mean": 644.2662963867188,
  "summary_fg_median": 592.6849365234375,
  "summary_fg_n": 394438.0,
  "summary_fg_p05": 319.75728302001954,
  "summary_fg_p95": 1163.1070312499996,
  "summary_fg_stdv": 269.6815185546875,
  "tsnr": 17.21214070194401
}